circle/__init__.py
circle/api_client.py
circle/configuration.py
circle/exceptions.py
circle/rest.py
circle/schemas.py
circle/apis/__init__.py
circle/apis/path_to_api.py
circle/apis/tag_to_api.py
circle/apis/paths/__init__.py
circle/apis/paths/ping.py
circle/apis/paths/v1_address_book_recipients.py
circle/apis/paths/v1_address_book_recipients_id.py
circle/apis/paths/v1_balances.py
circle/apis/paths/v1_business_account_balances.py
circle/apis/paths/v1_business_account_banks_cbit.py
circle/apis/paths/v1_business_account_banks_cbit_id.py
circle/apis/paths/v1_business_account_banks_cbit_id_instructions.py
circle/apis/paths/v1_business_account_banks_wires.py
circle/apis/paths/v1_business_account_banks_wires_id.py
circle/apis/paths/v1_business_account_banks_wires_id_instructions.py
circle/apis/paths/v1_business_account_deposits.py
circle/apis/paths/v1_business_account_payouts.py
circle/apis/paths/v1_business_account_payouts_id.py
circle/apis/paths/v1_business_account_transfers.py
circle/apis/paths/v1_business_account_transfers_id.py
circle/apis/paths/v1_business_account_wallets_addresses_deposit.py
circle/apis/paths/v1_business_account_wallets_addresses_recipient.py
circle/apis/paths/v1_business_account_wallets_addresses_recipient_id.py
circle/apis/paths/v1_cards.py
circle/apis/paths/v1_cards_id.py
circle/apis/paths/v1_channels.py
circle/apis/paths/v1_chargebacks.py
circle/apis/paths/v1_chargebacks_id.py
circle/apis/paths/v1_checkout_sessions.py
circle/apis/paths/v1_checkout_sessions_id.py
circle/apis/paths/v1_checkout_sessions_id_extend.py
circle/apis/paths/v1_configuration.py
circle/apis/paths/v1_encryption_public.py
circle/apis/paths/v1_exchange_rates_trading_pair.py
circle/apis/paths/v1_mocks_cards_chargebacks.py
circle/apis/paths/v1_mocks_payments_wire.py
circle/apis/paths/v1_notifications_subscriptions.py
circle/apis/paths/v1_notifications_subscriptions_id.py
circle/apis/paths/v1_payment_intents.py
circle/apis/paths/v1_payment_intents_id.py
circle_sdk-0.1.0b14.dist-info/LICENSE
circle_sdk-0.1.0b14.dist-info/METADATA
circle_sdk-0.1.0b14.dist-info/WHEEL
circle_sdk-0.1.0b14.dist-info/top_level.txt
circle_sdk-0.1.0b14.dist-info/RECORD
